xecs_pygame/__init__.py
xecs_pygame/py.typed
xecs_pygame-2.0.1.dist-info/METADATA
xecs_pygame-2.0.1.dist-info/WHEEL
xecs_pygame-2.0.1.dist-info/top_level.txt
xecs_pygame-2.0.1.dist-info/RECORD
