Metadata-Version: 2.1
Name: xecs-pygame
Version: 2.0.1
Summary: A pygame plugin for xecs.
Maintainer-email: Lukas Turcani <lukasturcani93@gmail.com>
Project-URL: github, https://github.com/lukasturcani/xecs-pygame
Requires-Python: >=3.11
Requires-Dist: xecs
Requires-Dist: pygame
Requires-Dist: numpy
Provides-Extra: dev
Requires-Dist: black ; extra == 'dev'
Requires-Dist: ruff ; extra == 'dev'
Requires-Dist: mypy ; extra == 'dev'
Requires-Dist: build ; extra == 'dev'
Requires-Dist: twine ; extra == 'dev'
